{"CCODI_AUTO":{"0":"00000014","1":"00000007","2":null,"3":"80","4":"80","5":"80","6":null},"AUTORIDAD":{"0":"PARTIDO POLITICO NACIONAL PERU LIBRE","1":"FUERZA POPULAR","2":"TOTAL VOTOS VALIDOS","3":"VOTOS EN BLANCO","4":"VOTOS NULOS","5":"VOTOS IMPUGNADOS","6":"TOTAL VOTOS EMITIDOS"},"NLISTA":{"0":"1","1":"2","2":null,"3":null,"4":null,"5":null,"6":null},"congresal":{"0":"163","1":"30","2":"193","3":"4","4":"1","5":"0","6":"198"},"CON_VALIDOS":{"0":"84.456","1":"15.544","2":"100.000","3":null,"4":null,"5":null,"6":"97.475"},"CON_EMITIDOS":{"0":"82.323","1":"15.152","2":"97.475","3":"2.020","4":"0.505","5":"0.000","6":"100.000"}}